MANIFEST.in
README.rst
bluesnow.py
requirements.txt
setup.py
bluesnow.egg-info/PKG-INFO
bluesnow.egg-info/SOURCES.txt
bluesnow.egg-info/dependency_links.txt
bluesnow.egg-info/entry_points.txt
bluesnow.egg-info/requires.txt
bluesnow.egg-info/top_level.txt