Metadata-Version: 1.1
Name: bluesnow
Version: 0.1.1
Summary: Package your Python applications into a single script
Home-page: https://github.com/kirbyfan64/bluesnow
Author: Ryan Gonzalez
Author-email: rymg19@gmail.com
License: BSD
Platform: UNKNOWN
Classifier: Programming Language :: Python :: 3 :: Only
Classifier: License :: OSI Approved :: BSD License
